[{
    "courseName": "ILE Lab",
    "courseOER": "https://link_to_your_oer_resource.com",
    "courseLicense": "https://creativecommons.org/licenses/by/4.0/",
    "lessons": [
        {
            "id": "kai_history_test",
            "name": "1.1 History of Science",
            "topics": "Famous history figures",
            "allowRecycle": true,
            "learningObjectives": {
                "historical_context": 0.85,
                "research_significance": 0.85
            }
        },
        {
            "id": "kai_git_tutor",
            "name": "1.2: Introduction to Git",
            "topics": "Understanding Git",
            "allowRecycle": true,
            "learningObjectives": {
                "basic_git_concepts": 0.85,
                "basic_git_operations": 0.85,
                "branching_and_merging": 0.85,
                "remote_repositories": 0.85,
                "undoing_changes": 0.85,
                "collaboration_and_workflows": 0.85
            }
        },
        {
              "id": "sql_tutor",
                "name": "1.3: Introduction to Sql",
                "topics": "Understanding Sql",
                "allowRecycle": true,
                "learningObjectives": {
                    "basic_sql_concepts": 0.85,
                    "basic_sql_operations": 0.85
            }
        },
        {
            "id": "Group1_geography-of-Germany_tutor",
            "name": "1.3: Geography",
            "topics": "The Geography of Germany",
            "allowRecycle": true,
            "learningObjectives": {
                "general_knowledge": 0.85,
                "european_continent": 0.85
            }
        },
        {
            "id": "group2_latex",
            "name": "LaTeX 101",
            "topics": "LaTeX",
            "allowRecycle": false,
            "learningObjectives": {
                "greek_letters": 1.0,
                "formulars": 1.0,
                "keywords": 1.0,
                "latex_technicals": 1.0,
                "packages": 0.85
            }
        },
        {
            "id": "greek_tutor",
            "name": "Greek Tutor",
            "topics": "Domain Knowledge",
            "allowRecycle": false,
            "learningObjectives": {
                "basic_greek_concepts": 0.99

            }
                
        },
        {
            "id": "ml&ai",
            "name": "1.0 Fundamentals of ML & AI",
            "topics": "Fundamentals",
            "allowRecycle": true,
            "learningObjectives": {
                "ml_fundamentals": 0.85,
                "overfitting_knowledge": 0.85,
                "underfitting_knowledge": 0.85,
                "conceptual_differentiation": 0.85,
                "conceptual_integration": 0.85,
                "data_interpretation": 0.85,
                "analytical_reasoning": 0.85,
                "fact_checking_ML": 0.85,
                "generalization_understanding": 0.85
            }
        },
        {
            "id": "group5_driving_tutorial",
            "name": "Traffic Regulations and Signs",
            "topics": "Understanding the Traffic Rules and Signs",
            "allowRecycle": true,
            "learningObjectives": {
                "traffic_signs_and_signals": 0.85,
                "rules_of_the_road": 0.85
            }
        }
    ]
}]
